odoo/addons/stock_picking_report_header_repeater/README.rst
odoo/addons/stock_picking_report_header_repeater/__init__.py
odoo/addons/stock_picking_report_header_repeater/__manifest__.py
odoo/addons/stock_picking_report_header_repeater/i18n/es.po
odoo/addons/stock_picking_report_header_repeater/i18n/it.po
odoo/addons/stock_picking_report_header_repeater/i18n/stock_picking_report_header_repeater.pot
odoo/addons/stock_picking_report_header_repeater/readme/CONTRIBUTORS.rst
odoo/addons/stock_picking_report_header_repeater/readme/DESCRIPTION.rst
odoo/addons/stock_picking_report_header_repeater/static/description/icon.png
odoo/addons/stock_picking_report_header_repeater/static/description/index.html
odoo/addons/stock_picking_report_header_repeater/views/report_delivery_document.xml
odoo_addon_stock_picking_report_header_repeater-16.0.1.0.0.4.dist-info/METADATA
odoo_addon_stock_picking_report_header_repeater-16.0.1.0.0.4.dist-info/WHEEL
odoo_addon_stock_picking_report_header_repeater-16.0.1.0.0.4.dist-info/top_level.txt
odoo_addon_stock_picking_report_header_repeater-16.0.1.0.0.4.dist-info/RECORD
